{
	"Version": 3,
	"Meta": {
		"Duration": 10.967,
		"Fps": 30.0,
		"Loop": true,
		"AreBeziersRestricted": false,
		"CurveCount": 94,
		"TotalSegmentCount": 952,
		"TotalPointCount": 2822,
		"UserDataCount": 0,
		"TotalUserDataSize": 0
	},
	"Curves": [
		{
			"Target": "Parameter",
			"Id": "PARAM_ANGLE_X",
			"Segments": [
				0,
				0,
				1,
				0.278,
				0,
				0.556,
				6,
				0.833,
				6,
				1,
				1.089,
				6,
				1.344,
				6,
				1.6,
				6,
				1,
				1.744,
				6,
				1.889,
				10.97,
				2.033,
				13,
				1,
				2.178,
				15.03,
				2.322,
				15.911,
				2.467,
				17,
				1,
				2.667,
				18.508,
				2.867,
				19,
				3.067,
				19,
				1,
				3.356,
				19,
				3.644,
				17.237,
				3.933,
				12,
				1,
				4.067,
				9.583,
				4.2,
				4.959,
				4.333,
				2,
				1,
				4.467,
				-0.959,
				4.6,
				-2,
				4.733,
				-2,
				1,
				4.9,
				-2,
				5.067,
				-2,
				5.233,
				-2,
				1,
				5.4,
				-2,
				5.567,
				0,
				5.733,
				0,
				1,
				5.911,
				0,
				6.089,
				0,
				6.267,
				0,
				1,
				6.467,
				0,
				6.667,
				-0.05,
				6.867,
				1,
				1,
				7,
				1.7,
				7.133,
				14,
				7.267,
				14,
				1,
				7.444,
				14,
				7.622,
				14,
				7.8,
				14,
				1,
				7.978,
				14,
				8.156,
				14,
				8.333,
				14,
				1,
				8.522,
				14,
				8.711,
				3,
				8.9,
				3,
				1,
				9.111,
				3,
				9.322,
				3,
				9.533,
				3,
				1,
				9.689,
				3,
				9.844,
				3,
				10,
				3,
				1,
				10.2,
				3,
				10.4,
				2.23,
				10.6,
				1,
				1,
				10.722,
				0.249,
				10.844,
				0,
				10.967,
				0
			]
		},
		{
			"Target": "Parameter",
			"Id": "PARAM_ANGLE_Y",
			"Segments": [
				0,
				0,
				1,
				0.167,
				0,
				0.333,
				17,
				0.5,
				17,
				1,
				0.622,
				17,
				0.744,
				-7,
				0.867,
				-7,
				1,
				1.122,
				-7,
				1.378,
				-3,
				1.633,
				-3,
				1,
				1.778,
				-3,
				1.922,
				-5.512,
				2.067,
				-8,
				1,
				2.211,
				-10.488,
				2.356,
				-11,
				2.5,
				-11,
				1,
				2.7,
				-11,
				2.9,
				-11,
				3.1,
				-11,
				1,
				3.389,
				-11,
				3.678,
				-10.95,
				3.967,
				-10,
				1,
				4.1,
				-9.561,
				4.233,
				11,
				4.367,
				11,
				1,
				4.5,
				11,
				4.633,
				0,
				4.767,
				0,
				1,
				4.933,
				0,
				5.1,
				3,
				5.267,
				3,
				1,
				5.433,
				3,
				5.6,
				-4,
				5.767,
				-4,
				1,
				5.944,
				-4,
				6.122,
				-4,
				6.3,
				-4,
				1,
				6.411,
				-4,
				6.522,
				9.42,
				6.633,
				11,
				1,
				6.722,
				12.264,
				6.811,
				12,
				6.9,
				12,
				1,
				7.033,
				12,
				7.167,
				-8,
				7.3,
				-8,
				1,
				7.478,
				-8,
				7.656,
				-8,
				7.833,
				-8,
				1,
				8.011,
				-8,
				8.189,
				-7.242,
				8.367,
				-5,
				1,
				8.767,
				0.044,
				9.167,
				3,
				9.567,
				3,
				1,
				9.711,
				3,
				9.856,
				3,
				10,
				3,
				1,
				10.089,
				3,
				10.178,
				-2,
				10.267,
				-2,
				1,
				10.378,
				-2,
				10.489,
				8,
				10.6,
				8,
				1,
				10.722,
				8,
				10.844,
				0,
				10.967,
				0
			]
		},
		{
			"Target": "Parameter",
			"Id": "PARAM_ANGLE_Z",
			"Segments": [
				0,
				0,
				1,
				0.267,
				0,
				0.533,
				14.697,
				0.8,
				16,
				1,
				1.056,
				17.249,
				1.311,
				17,
				1.567,
				17,
				1,
				1.711,
				17,
				1.856,
				17,
				2,
				17,
				1,
				2.344,
				17,
				2.689,
				18,
				3.033,
				18,
				1,
				3.322,
				18,
				3.611,
				17.7,
				3.9,
				16,
				1,
				4.033,
				15.215,
				4.167,
				12.568,
				4.3,
				10,
				1,
				4.433,
				7.432,
				4.567,
				-0.153,
				4.7,
				-1,
				1,
				4.867,
				-2.059,
				5.033,
				-2,
				5.2,
				-2,
				1,
				5.367,
				-2,
				5.533,
				18,
				5.7,
				18,
				1,
				5.878,
				18,
				6.056,
				17.211,
				6.233,
				15,
				1,
				6.344,
				13.618,
				6.456,
				10.709,
				6.567,
				10,
				1,
				6.656,
				9.433,
				6.744,
				9.691,
				6.833,
				9,
				1,
				6.967,
				7.963,
				7.1,
				-1.431,
				7.233,
				-4,
				1,
				7.411,
				-7.425,
				7.589,
				-8,
				7.767,
				-8,
				1,
				7.944,
				-8,
				8.122,
				-8.228,
				8.3,
				-7,
				1,
				8.489,
				-5.695,
				8.678,
				17.96,
				8.867,
				19,
				1,
				9.078,
				20.163,
				9.289,
				20,
				9.5,
				20,
				1,
				9.667,
				20,
				9.833,
				20,
				10,
				20,
				1,
				10.322,
				20,
				10.644,
				0,
				10.967,
				0
			]
		},
		{
			"Target": "Parameter",
			"Id": "PARAM_BODY_ANGLE_X",
			"Segments": [
				0,
				0,
				1,
				0.233,
				0,
				0.467,
				3.04,
				0.7,
				4,
				1,
				0.956,
				5.051,
				1.211,
				5,
				1.467,
				5,
				1,
				1.611,
				5,
				1.756,
				4.931,
				1.9,
				4,
				1,
				2.244,
				1.78,
				2.589,
				0,
				2.933,
				0,
				1,
				3.222,
				0,
				3.511,
				4,
				3.8,
				4,
				1,
				4.067,
				4,
				4.333,
				0,
				4.6,
				0,
				1,
				4.767,
				0,
				4.933,
				0,
				5.1,
				0,
				1,
				5.267,
				0,
				5.433,
				1,
				5.6,
				1,
				1,
				5.778,
				1,
				5.956,
				0,
				6.133,
				0,
				1,
				6.333,
				0,
				6.533,
				0.037,
				6.733,
				1,
				1,
				6.867,
				1.642,
				7,
				6.482,
				7.133,
				7,
				1,
				7.311,
				7.69,
				7.489,
				7.669,
				7.667,
				7.669,
				1,
				7.844,
				7.669,
				8.022,
				7.862,
				8.2,
				7,
				1,
				8.6,
				5.061,
				9,
				2,
				9.4,
				2,
				1,
				9.6,
				2,
				9.8,
				2,
				10,
				2,
				1,
				10.322,
				2,
				10.644,
				0,
				10.967,
				0
			]
		},
		{
			"Target": "Parameter",
			"Id": "PARAM_BODY_ANGLE_Y",
			"Segments": [
				0,
				0,
				1,
				0.133,
				0,
				0.267,
				4,
				0.4,
				4,
				1,
				0.522,
				4,
				0.644,
				1,
				0.767,
				1,
				1,
				1.022,
				1,
				1.278,
				2,
				1.533,
				2,
				1,
				1.678,
				2,
				1.822,
				2,
				1.967,
				2,
				1,
				2.311,
				2,
				2.656,
				3,
				3,
				3,
				1,
				3.289,
				3,
				3.578,
				0,
				3.867,
				0,
				1,
				4,
				0,
				4.133,
				6,
				4.267,
				6,
				1,
				4.4,
				6,
				4.533,
				0,
				4.667,
				0,
				1,
				4.833,
				0,
				5,
				1,
				5.167,
				1,
				1,
				5.333,
				1,
				5.5,
				-1,
				5.667,
				-1,
				1,
				5.844,
				-1,
				6.022,
				-1,
				6.2,
				-1,
				1,
				6.311,
				-1,
				6.422,
				0.776,
				6.533,
				2,
				1,
				6.622,
				2.979,
				6.711,
				3,
				6.8,
				3,
				1,
				7.289,
				3,
				7.778,
				2.889,
				8.267,
				2,
				1,
				8.456,
				1.656,
				8.644,
				-2,
				8.833,
				-2,
				1,
				9.044,
				-2,
				9.256,
				-1,
				9.467,
				-1,
				1,
				9.644,
				-1,
				9.822,
				-1,
				10,
				-1,
				1,
				10.156,
				-1,
				10.311,
				1,
				10.467,
				1,
				1,
				10.633,
				1,
				10.8,
				0,
				10.967,
				0
			]
		},
		{
			"Target": "Parameter",
			"Id": "PARAM_BODY_ANGLE_Z",
			"Segments": [
				0,
				0,
				1,
				0.222,
				0,
				0.444,
				0.99,
				0.667,
				1,
				1,
				0.922,
				1.011,
				1.178,
				1.009,
				1.433,
				1.009,
				1,
				1.578,
				1.009,
				1.722,
				1.009,
				1.867,
				1.009,
				1,
				2.211,
				1.009,
				2.556,
				0.766,
				2.9,
				0.766,
				1,
				3.189,
				0.766,
				3.478,
				0.785,
				3.767,
				1,
				1,
				4.033,
				1.198,
				4.3,
				1.954,
				4.567,
				2,
				1,
				4.733,
				2.029,
				4.9,
				2.018,
				5.067,
				2.018,
				1,
				5.233,
				2.018,
				5.4,
				0.979,
				5.567,
				0.979,
				1,
				5.744,
				0.979,
				5.922,
				0.971,
				6.1,
				1,
				1,
				6.3,
				1.033,
				6.5,
				2,
				6.7,
				2,
				1,
				6.833,
				2,
				6.967,
				1.061,
				7.1,
				1,
				1,
				7.278,
				0.919,
				7.456,
				0.927,
				7.633,
				0.927,
				1,
				7.811,
				0.927,
				7.989,
				1,
				8.167,
				1,
				1,
				8.356,
				1,
				8.544,
				0,
				8.733,
				0,
				1,
				8.944,
				0,
				9.156,
				0,
				9.367,
				0,
				1,
				9.578,
				0,
				9.789,
				0,
				10,
				0,
				1,
				10.322,
				0,
				10.644,
				0,
				10.967,
				0
			]
		},
		{
			"Target": "Parameter",
			"Id": "PARAM_BODY_weiyi",
			"Segments": [
				0,
				0,
				1,
				0.233,
				0,
				0.467,
				0.129,
				0.7,
				0.13,
				1,
				0.956,
				0.132,
				1.211,
				0.131,
				1.467,
				0.131,
				1,
				1.611,
				0.131,
				1.756,
				0.131,
				1.9,
				0.131,
				1,
				2.244,
				0.131,
				2.589,
				0.104,
				2.933,
				0.064,
				1,
				3.222,
				0.031,
				3.511,
				0.02,
				3.8,
				0.02,
				1,
				4.067,
				0.02,
				4.333,
				0.58,
				4.6,
				0.58,
				1,
				4.767,
				0.58,
				4.933,
				0.58,
				5.1,
				0.58,
				1,
				5.267,
				0.58,
				5.433,
				-0.1,
				5.6,
				-0.1,
				1,
				5.778,
				-0.1,
				5.956,
				-0.1,
				6.133,
				-0.1,
				1,
				6.244,
				-0.1,
				6.356,
				-0.16,
				6.467,
				-0.16,
				1,
				6.556,
				-0.16,
				6.644,
				-0.15,
				6.733,
				-0.15,
				1,
				6.867,
				-0.15,
				7,
				-0.2,
				7.133,
				-0.2,
				1,
				7.311,
				-0.2,
				7.489,
				-0.2,
				7.667,
				-0.2,
				1,
				7.844,
				-0.2,
				8.022,
				-0.2,
				8.2,
				-0.2,
				1,
				8.389,
				-0.2,
				8.578,
				-0.15,
				8.767,
				-0.15,
				1,
				8.978,
				-0.15,
				9.189,
				-0.15,
				9.4,
				-0.15,
				1,
				9.6,
				-0.15,
				9.8,
				-0.15,
				10,
				-0.15,
				1,
				10.322,
				-0.15,
				10.644,
				0,
				10.967,
				0
			]
		},
		{
			"Target": "Parameter",
			"Id": "PARAM_EYE_L_OPEN",
			"Segments": [
				0,
				1,
				1,
				0.1,
				1,
				0.2,
				0.968,
				0.3,
				0.93,
				1,
				0.378,
				0.901,
				0.456,
				0.902,
				0.533,
				0.86,
				1,
				0.6,
				0.824,
				0.667,
				0,
				0.733,
				0,
				1,
				0.844,
				0,
				0.956,
				0,
				1.067,
				0,
				1,
				1.156,
				0,
				1.244,
				0.86,
				1.333,
				0.86,
				1,
				1.756,
				0.86,
				2.178,
				0.86,
				2.6,
				0.86,
				1,
				2.678,
				0.86,
				2.756,
				0,
				2.833,
				0,
				1,
				2.911,
				0,
				2.989,
				1,
				3.067,
				1,
				1,
				3.344,
				1,
				3.622,
				1,
				3.9,
				1,
				1,
				4.022,
				1,
				4.144,
				0.85,
				4.267,
				0.85,
				1,
				4.944,
				0.85,
				5.622,
				0.85,
				6.3,
				0.85,
				1,
				6.367,
				0.85,
				6.433,
				0,
				6.5,
				0,
				1,
				6.567,
				0,
				6.633,
				0.85,
				6.7,
				0.85,
				1,
				7.8,
				0.85,
				8.9,
				0.85,
				10,
				0.85,
				1,
				10.067,
				0.85,
				10.133,
				1,
				10.2,
				1,
				1,
				10.456,
				1,
				10.711,
				1,
				10.967,
				1
			]
		},
		{
			"Target": "Parameter",
			"Id": "PARAM_EYE_L_SMILE",
			"Segments": [
				0,
				0,
				1,
				0.1,
				0,
				0.2,
				0,
				0.3,
				0,
				1,
				0.644,
				0,
				0.989,
				0,
				1.333,
				0,
				1,
				1.756,
				0,
				2.178,
				0,
				2.6,
				0,
				1,
				5.067,
				0,
				7.533,
				0,
				10,
				0,
				1,
				10.322,
				0,
				10.644,
				0,
				10.967,
				0
			]
		},
		{
			"Target": "Parameter",
			"Id": "PARAM_EYE_R_OPEN",
			"Segments": [
				0,
				1,
				1,
				0.1,
				1,
				0.2,
				0.956,
				0.3,
				0.92,
				1,
				0.378,
				0.892,
				0.456,
				0.896,
				0.533,
				0.86,
				1,
				0.6,
				0.829,
				0.667,
				0,
				0.733,
				0,
				1,
				0.844,
				0,
				0.956,
				0,
				1.067,
				0,
				1,
				1.156,
				0,
				1.244,
				0.86,
				1.333,
				0.86,
				1,
				1.756,
				0.86,
				2.178,
				0.86,
				2.6,
				0.86,
				1,
				2.678,
				0.86,
				2.756,
				0,
				2.833,
				0,
				1,
				2.911,
				0,
				2.989,
				1,
				3.067,
				1,
				1,
				3.344,
				1,
				3.622,
				1,
				3.9,
				1,
				1,
				4.022,
				1,
				4.144,
				0.87,
				4.267,
				0.87,
				1,
				4.944,
				0.87,
				5.622,
				0.87,
				6.3,
				0.87,
				1,
				6.367,
				0.87,
				6.433,
				0,
				6.5,
				0,
				1,
				6.567,
				0,
				6.633,
				0.87,
				6.7,
				0.87,
				1,
				7.8,
				0.87,
				8.9,
				0.87,
				10,
				0.87,
				1,
				10.067,
				0.87,
				10.133,
				1,
				10.2,
				1,
				1,
				10.456,
				1,
				10.711,
				1,
				10.967,
				1
			]
		},
		{
			"Target": "Parameter",
			"Id": "PARAM_EYE_R_SMILE",
			"Segments": [
				0,
				0,
				1,
				0.1,
				0,
				0.2,
				0,
				0.3,
				0,
				1,
				0.644,
				0,
				0.989,
				0,
				1.333,
				0,
				1,
				1.756,
				0,
				2.178,
				0,
				2.6,
				0,
				1,
				5.067,
				0,
				7.533,
				0,
				10,
				0,
				1,
				10.322,
				0,
				10.644,
				0,
				10.967,
				0
			]
		},
		{
			"Target": "Parameter",
			"Id": "PARAM_EYE_BALL_X",
			"Segments": [
				0,
				0,
				1,
				0.1,
				0,
				0.2,
				0,
				0.3,
				0,
				1,
				0.644,
				0,
				0.989,
				0.85,
				1.333,
				0.85,
				1,
				1.756,
				0.85,
				2.178,
				0.85,
				2.6,
				0.85,
				1,
				2.689,
				0.85,
				2.778,
				0.271,
				2.867,
				0,
				1,
				2.933,
				-0.203,
				3,
				-0.18,
				3.067,
				-0.18,
				1,
				3.344,
				-0.18,
				3.622,
				-0.18,
				3.9,
				-0.18,
				1,
				4,
				-0.18,
				4.1,
				0,
				4.2,
				0,
				1,
				5.011,
				0,
				5.822,
				0,
				6.633,
				0,
				1,
				6.8,
				0,
				6.967,
				0.14,
				7.133,
				0.14,
				1,
				7.567,
				0.14,
				8,
				0.14,
				8.433,
				0.14,
				1,
				8.544,
				0.14,
				8.656,
				0,
				8.767,
				0,
				1,
				9.178,
				0,
				9.589,
				0,
				10,
				0,
				1,
				10.322,
				0,
				10.644,
				0,
				10.967,
				0
			]
		},
		{
			"Target": "Parameter",
			"Id": "PARAM_EYE_BALL_Y",
			"Segments": [
				0,
				0,
				1,
				0.1,
				0,
				0.2,
				0,
				0.3,
				0,
				1,
				0.644,
				0,
				0.989,
				-0.25,
				1.333,
				-0.25,
				1,
				1.756,
				-0.25,
				2.178,
				-0.25,
				2.6,
				-0.25,
				1,
				2.689,
				-0.25,
				2.778,
				0,
				2.867,
				0,
				1,
				2.933,
				0,
				3,
				-0.04,
				3.067,
				-0.04,
				1,
				3.344,
				-0.04,
				3.622,
				-0.04,
				3.9,
				-0.04,
				1,
				4,
				-0.04,
				4.1,
				0,
				4.2,
				0,
				1,
				5.011,
				0,
				5.822,
				0,
				6.633,
				0,
				1,
				6.8,
				0,
				6.967,
				-0.42,
				7.133,
				-0.42,
				1,
				7.567,
				-0.42,
				8,
				-0.42,
				8.433,
				-0.42,
				1,
				8.544,
				-0.42,
				8.656,
				0,
				8.767,
				0,
				1,
				9.178,
				0,
				9.589,
				0,
				10,
				0,
				1,
				10.322,
				0,
				10.644,
				0,
				10.967,
				0
			]
		},
		{
			"Target": "Parameter",
			"Id": "PARAM_EYE_SIZE",
			"Segments": [
				0,
				0,
				1,
				0.444,
				0,
				0.889,
				0,
				1.333,
				0,
				1,
				1.756,
				0,
				2.178,
				0,
				2.6,
				0,
				1,
				3.833,
				0,
				5.067,
				0,
				6.3,
				0,
				1,
				6.433,
				0,
				6.567,
				0,
				6.7,
				0,
				1,
				7.8,
				0,
				8.9,
				0,
				10,
				0,
				1,
				10.322,
				0,
				10.644,
				0,
				10.967,
				0
			]
		},
		{
			"Target": "Parameter",
			"Id": "PARAM_BROW_L_Y",
			"Segments": [
				0,
				0,
				1,
				0.178,
				0,
				0.356,
				0,
				0.533,
				0,
				1,
				0.6,
				0,
				0.667,
				-0.72,
				0.733,
				-0.72,
				1,
				0.844,
				-0.72,
				0.956,
				-0.72,
				1.067,
				-0.72,
				1,
				1.156,
				-0.72,
				1.244,
				0,
				1.333,
				0,
				1,
				1.756,
				0,
				2.178,
				0,
				2.6,
				0,
				1,
				2.678,
				0,
				2.756,
				-0.7,
				2.833,
				-0.7,
				1,
				2.911,
				-0.7,
				2.989,
				0,
				3.067,
				0,
				1,
				3.344,
				0,
				3.622,
				0,
				3.9,
				0,
				1,
				4.022,
				0,
				4.144,
				-0.12,
				4.267,
				-0.12,
				1,
				4.944,
				-0.12,
				5.622,
				-0.12,
				6.3,
				-0.12,
				1,
				6.367,
				-0.12,
				6.433,
				-0.9,
				6.5,
				-0.9,
				1,
				6.567,
				-0.9,
				6.633,
				-0.12,
				6.7,
				-0.12,
				1,
				7.8,
				-0.12,
				8.9,
				-0.12,
				10,
				-0.12,
				1,
				10.067,
				-0.12,
				10.133,
				0,
				10.2,
				0,
				1,
				10.456,
				0,
				10.711,
				0,
				10.967,
				0
			]
		},
		{
			"Target": "Parameter",
			"Id": "PARAM_BROW_R_Y",
			"Segments": [
				0,
				0,
				1,
				0.178,
				0,
				0.356,
				0,
				0.533,
				0,
				1,
				0.6,
				0,
				0.667,
				-0.74,
				0.733,
				-0.74,
				1,
				0.844,
				-0.74,
				0.956,
				-0.74,
				1.067,
				-0.74,
				1,
				1.156,
				-0.74,
				1.244,
				0,
				1.333,
				0,
				1,
				1.756,
				0,
				2.178,
				0,
				2.6,
				0,
				1,
				2.678,
				0,
				2.756,
				-0.7,
				2.833,
				-0.7,
				1,
				2.911,
				-0.7,
				2.989,
				0,
				3.067,
				0,
				1,
				3.344,
				0,
				3.622,
				0,
				3.9,
				0,
				1,
				4.022,
				0,
				4.144,
				-0.1,
				4.267,
				-0.1,
				1,
				4.944,
				-0.1,
				5.622,
				-0.1,
				6.3,
				-0.1,
				1,
				6.367,
				-0.1,
				6.433,
				-0.83,
				6.5,
				-0.83,
				1,
				6.567,
				-0.83,
				6.633,
				-0.1,
				6.7,
				-0.1,
				1,
				7.8,
				-0.1,
				8.9,
				-0.1,
				10,
				-0.1,
				1,
				10.067,
				-0.1,
				10.133,
				0,
				10.2,
				0,
				1,
				10.456,
				0,
				10.711,
				0,
				10.967,
				0
			]
		},
		{
			"Target": "Parameter",
			"Id": "PARAM_BROW_R_X",
			"Segments": [
				0,
				0,
				1,
				0.178,
				0,
				0.356,
				-0.02,
				0.533,
				-0.02,
				1,
				0.6,
				-0.02,
				0.667,
				0,
				0.733,
				0,
				1,
				0.844,
				0,
				0.956,
				0,
				1.067,
				0,
				1,
				1.156,
				0,
				1.244,
				0,
				1.333,
				0,
				1,
				1.756,
				0,
				2.178,
				0,
				2.6,
				0,
				1,
				3.033,
				0,
				3.467,
				0,
				3.9,
				0,
				1,
				4.7,
				0,
				5.5,
				0,
				6.3,
				0,
				1,
				6.433,
				0,
				6.567,
				0,
				6.7,
				0,
				1,
				7.8,
				0,
				8.9,
				0,
				10,
				0,
				1,
				10.322,
				0,
				10.644,
				0,
				10.967,
				0
			]
		},
		{
			"Target": "Parameter",
			"Id": "PARAM_BROW_L_X",
			"Segments": [
				0,
				0,
				1,
				0.178,
				0,
				0.356,
				0,
				0.533,
				0,
				1,
				0.6,
				0,
				0.667,
				0,
				0.733,
				0,
				1,
				0.844,
				0,
				0.956,
				0,
				1.067,
				0,
				1,
				1.156,
				0,
				1.244,
				0,
				1.333,
				0,
				1,
				1.756,
				0,
				2.178,
				0,
				2.6,
				0,
				1,
				3.033,
				0,
				3.467,
				0,
				3.9,
				0,
				1,
				4.7,
				0,
				5.5,
				0,
				6.3,
				0,
				1,
				6.433,
				0,
				6.567,
				0,
				6.7,
				0,
				1,
				7.8,
				0,
				8.9,
				0,
				10,
				0,
				1,
				10.322,
				0,
				10.644,
				0,
				10.967,
				0
			]
		},
		{
			"Target": "Parameter",
			"Id": "PARAM_BROW_L_ANGLE",
			"Segments": [
				0,
				0,
				1,
				0.178,
				0,
				0.356,
				0.07,
				0.533,
				0.07,
				1,
				0.6,
				0.07,
				0.667,
				-0.03,
				0.733,
				-0.03,
				1,
				0.844,
				-0.03,
				0.956,
				-0.03,
				1.067,
				-0.03,
				1,
				1.156,
				-0.03,
				1.244,
				0.07,
				1.333,
				0.07,
				1,
				1.756,
				0.07,
				2.178,
				0.07,
				2.6,
				0.07,
				1,
				2.756,
				0.07,
				2.911,
				0,
				3.067,
				0,
				1,
				3.344,
				0,
				3.622,
				0,
				3.9,
				0,
				1,
				4.022,
				0,
				4.144,
				0.06,
				4.267,
				0.06,
				1,
				4.944,
				0.06,
				5.622,
				0.06,
				6.3,
				0.06,
				1,
				6.367,
				0.06,
				6.433,
				-0.04,
				6.5,
				-0.04,
				1,
				6.567,
				-0.04,
				6.633,
				0.06,
				6.7,
				0.06,
				1,
				7.8,
				0.06,
				8.9,
				0.06,
				10,
				0.06,
				1,
				10.067,
				0.06,
				10.133,
				0,
				10.2,
				0,
				1,
				10.456,
				0,
				10.711,
				0,
				10.967,
				0
			]
		},
		{
			"Target": "Parameter",
			"Id": "PARAM_BROW_R_ANGLE",
			"Segments": [
				0,
				0,
				1,
				0.178,
				0,
				0.356,
				-0.15,
				0.533,
				-0.15,
				1,
				0.6,
				-0.15,
				0.667,
				-0.1,
				0.733,
				-0.1,
				1,
				0.844,
				-0.1,
				0.956,
				-0.1,
				1.067,
				-0.1,
				1,
				1.156,
				-0.1,
				1.244,
				-0.15,
				1.333,
				-0.15,
				1,
				1.756,
				-0.15,
				2.178,
				-0.15,
				2.6,
				-0.15,
				1,
				2.756,
				-0.15,
				2.911,
				0,
				3.067,
				0,
				1,
				3.344,
				0,
				3.622,
				0,
				3.9,
				0,
				1,
				4.022,
				0,
				4.144,
				-0.13,
				4.267,
				-0.13,
				1,
				4.944,
				-0.13,
				5.622,
				-0.13,
				6.3,
				-0.13,
				1,
				6.367,
				-0.13,
				6.433,
				0.01,
				6.5,
				0.01,
				1,
				6.567,
				0.01,
				6.633,
				-0.13,
				6.7,
				-0.13,
				1,
				7.8,
				-0.13,
				8.9,
				-0.13,
				10,
				-0.13,
				1,
				10.067,
				-0.13,
				10.133,
				0,
				10.2,
				0,
				1,
				10.456,
				0,
				10.711,
				0,
				10.967,
				0
			]
		},
		{
			"Target": "Parameter",
			"Id": "PARAM_BROW_L_FORM",
			"Segments": [
				0,
				0,
				1,
				0.178,
				0,
				0.356,
				0,
				0.533,
				0,
				1,
				0.8,
				0,
				1.067,
				0,
				1.333,
				0,
				1,
				1.756,
				0,
				2.178,
				0,
				2.6,
				0,
				1,
				2.678,
				0,
				2.756,
				0,
				2.833,
				0,
				1,
				3.189,
				0,
				3.544,
				0,
				3.9,
				0,
				1,
				4.022,
				0,
				4.144,
				-0.1,
				4.267,
				-0.1,
				1,
				4.944,
				-0.1,
				5.622,
				-0.1,
				6.3,
				-0.1,
				1,
				6.433,
				-0.1,
				6.567,
				-0.1,
				6.7,
				-0.1,
				1,
				7.8,
				-0.1,
				8.9,
				-0.1,
				10,
				-0.1,
				1,
				10.067,
				-0.1,
				10.133,
				0,
				10.2,
				0,
				1,
				10.456,
				0,
				10.711,
				0,
				10.967,
				0
			]
		},
		{
			"Target": "Parameter",
			"Id": "PARAM_BROW_R_FORM",
			"Segments": [
				0,
				0,
				1,
				0.178,
				0,
				0.356,
				0,
				0.533,
				0,
				1,
				0.8,
				0,
				1.067,
				0,
				1.333,
				0,
				1,
				1.756,
				0,
				2.178,
				0,
				2.6,
				0,
				1,
				2.678,
				0,
				2.756,
				0,
				2.833,
				0,
				1,
				3.189,
				0,
				3.544,
				0,
				3.9,
				0,
				1,
				4.022,
				0,
				4.144,
				-0.05,
				4.267,
				-0.05,
				1,
				4.944,
				-0.05,
				5.622,
				-0.05,
				6.3,
				-0.05,
				1,
				6.433,
				-0.05,
				6.567,
				-0.05,
				6.7,
				-0.05,
				1,
				7.8,
				-0.05,
				8.9,
				-0.05,
				10,
				-0.05,
				1,
				10.067,
				-0.05,
				10.133,
				0,
				10.2,
				0,
				1,
				10.456,
				0,
				10.711,
				0,
				10.967,
				0
			]
		},
		{
			"Target": "Parameter",
			"Id": "PARAM_MOUTH_FORM",
			"Segments": [
				0,
				0,
				1,
				0.167,
				0,
				0.333,
				0.53,
				0.5,
				0.53,
				1,
				1.578,
				0.53,
				2.656,
				0.52,
				3.733,
				0.52,
				1,
				3.867,
				0.52,
				4,
				0.75,
				4.133,
				0.75,
				1,
				6.089,
				0.75,
				8.044,
				0.75,
				10,
				0.75,
				1,
				10.067,
				0.75,
				10.133,
				0,
				10.2,
				0,
				1,
				10.456,
				0,
				10.711,
				0,
				10.967,
				0
			]
		},
		{
			"Target": "Parameter",
			"Id": "PARAM_MOUTH_OPEN_Y",
			"Segments": [
				0,
				0,
				1,
				0.067,
				-0.004,
				0.133,
				0.206,
				0.2,
				0.949,
				3,
				0.233,
				1,
				0,
				0.633,
				1,
				1,
				0.644,
				0.971,
				0.656,
				1.076,
				0.667,
				0.89,
				1,
				0.678,
				0.791,
				0.689,
				0.67,
				0.7,
				0.578,
				1,
				0.733,
				0.279,
				0.767,
				0.039,
				0.8,
				0.039,
				1,
				0.844,
				0.033,
				0.889,
				0.877,
				0.933,
				0.871,
				0,
				1,
				0.839,
				1,
				1.011,
				0.824,
				1.022,
				1.101,
				1.033,
				1,
				0,
				1.1,
				1,
				2,
				1.133,
				0.867,
				1,
				1.156,
				0.47,
				1.178,
				0.103,
				1.2,
				0.094,
				1,
				1.233,
				0.025,
				1.267,
				1.007,
				1.3,
				1,
				0,
				1.5,
				1,
				1,
				1.511,
				1.075,
				1.522,
				0.873,
				1.533,
				0.855,
				1,
				1.544,
				0.851,
				1.556,
				1.086,
				1.567,
				1,
				0,
				1.633,
				1,
				2,
				1.667,
				0.965,
				3,
				1.7,
				1,
				0,
				1.767,
				1,
				1,
				1.778,
				0.744,
				1.789,
				0.433,
				1.8,
				0.447,
				1,
				1.822,
				0.453,
				1.844,
				0.685,
				1.867,
				0.937,
				3,
				1.9,
				1,
				0,
				1.967,
				1,
				1,
				2,
				1.062,
				2.033,
				0.081,
				2.067,
				0.157,
				1,
				2.078,
				0.129,
				2.089,
				0.634,
				2.1,
				1,
				0,
				2.3,
				1,
				1,
				2.333,
				0.924,
				2.367,
				-0.057,
				2.4,
				0,
				1,
				2.411,
				-0.014,
				2.422,
				0.323,
				2.433,
				0.612,
				1,
				2.444,
				1.03,
				2.456,
				1.017,
				2.467,
				1,
				0,
				2.7,
				1,
				1,
				2.711,
				1.017,
				2.722,
				0.622,
				2.733,
				0.675,
				1,
				2.756,
				0.679,
				2.778,
				0.983,
				2.8,
				0.988,
				1,
				2.822,
				0.979,
				2.844,
				0.409,
				2.867,
				0.4,
				1,
				2.878,
				0.351,
				2.889,
				0.85,
				2.9,
				1,
				0,
				2.967,
				1,
				1,
				2.978,
				1.193,
				2.989,
				0.603,
				3,
				0.698,
				1,
				3.022,
				0.7,
				3.044,
				0.791,
				3.067,
				0.792,
				1,
				3.111,
				0.798,
				3.156,
				-0.006,
				3.2,
				0,
				0,
				3.6,
				0,
				1,
				3.633,
				0.011,
				3.667,
				0.452,
				3.7,
				0.929,
				3,
				3.733,
				1,
				0,
				3.867,
				1,
				2,
				3.9,
				0.979,
				1,
				3.911,
				0.885,
				3.922,
				0.812,
				3.933,
				0.816,
				1,
				3.956,
				0.8,
				3.978,
				1.104,
				4,
				1,
				1,
				4.022,
				1.092,
				4.044,
				0.02,
				4.067,
				0.024,
				1,
				4.078,
				0.005,
				4.089,
				0.435,
				4.1,
				0.804,
				3,
				4.133,
				1,
				0,
				4.3,
				1,
				2,
				4.333,
				0.82,
				1,
				4.356,
				0.399,
				4.378,
				0.01,
				4.4,
				0,
				1,
				4.422,
				0.011,
				4.444,
				0.452,
				4.467,
				0.929,
				3,
				4.5,
				1,
				0,
				4.567,
				1,
				2,
				4.6,
				0.929,
				1,
				4.622,
				0.452,
				4.644,
				0.011,
				4.667,
				0,
				0,
				4.867,
				0,
				1,
				4.889,
				-0.001,
				4.911,
				0.175,
				4.933,
				0.396,
				1,
				4.944,
				0.51,
				4.956,
				0.646,
				4.967,
				0.769,
				1,
				4.978,
				0.875,
				4.989,
				1.082,
				5,
				1,
				0,
				5.1,
				1,
				1,
				5.133,
				1.112,
				5.167,
				-0.099,
				5.2,
				0,
				1,
				5.233,
				-0.057,
				5.267,
				0.924,
				5.3,
				1,
				0,
				5.367,
				1,
				1,
				5.378,
				0.925,
				5.389,
				0.682,
				5.4,
				0.706,
				1,
				5.411,
				0.636,
				5.422,
				1.101,
				5.433,
				1,
				0,
				5.467,
				1,
				2,
				5.5,
				0.831,
				1,
				5.511,
				0.446,
				5.522,
				-0.003,
				5.533,
				0.016,
				1,
				5.556,
				0.017,
				5.578,
				0.077,
				5.6,
				0.078,
				1,
				5.622,
				0.077,
				5.644,
				0.001,
				5.667,
				0,
				0,
				5.8,
				0,
				0,
				5.867,
				0.031,
				0,
				5.933,
				0,
				0,
				6.067,
				0,
				1,
				6.078,
				-0.014,
				6.089,
				0.308,
				6.1,
				0.584,
				1,
				6.111,
				0.931,
				6.122,
				1.069,
				6.133,
				1,
				1,
				6.144,
				1.03,
				6.156,
				0.995,
				6.167,
				0.671,
				1,
				6.178,
				0.435,
				6.189,
				0.161,
				6.2,
				0.173,
				1,
				6.211,
				0.127,
				6.222,
				0.71,
				6.233,
				1,
				0,
				6.3,
				1,
				2,
				6.333,
				0.988,
				1,
				6.356,
				0.481,
				6.378,
				0.012,
				6.4,
				0,
				0,
				6.667,
				0,
				1,
				6.689,
				0.01,
				6.711,
				0.418,
				6.733,
				0.859,
				3,
				6.767,
				1,
				0,
				6.833,
				1,
				2,
				6.867,
				0.898,
				1,
				6.889,
				0.477,
				6.911,
				0.088,
				6.933,
				0.078,
				1,
				6.956,
				0.08,
				6.978,
				0.187,
				7,
				0.188,
				1,
				7.022,
				0.186,
				7.044,
				0.072,
				7.067,
				0.071,
				1,
				7.089,
				0.081,
				7.111,
				0.494,
				7.133,
				0.941,
				3,
				7.167,
				1,
				0,
				7.367,
				1,
				2,
				7.4,
				0.973,
				1,
				7.422,
				0.477,
				7.444,
				0.019,
				7.467,
				0.008,
				1,
				7.478,
				-0.012,
				7.489,
				0.463,
				7.5,
				0.871,
				3,
				7.533,
				1,
				0,
				7.6,
				1,
				1,
				7.622,
				0.807,
				7.644,
				0.405,
				7.667,
				0.424,
				1,
				7.678,
				0.389,
				7.689,
				0.808,
				7.7,
				1,
				0,
				7.767,
				1,
				1,
				7.778,
				0.898,
				7.789,
				0.455,
				7.8,
				0.502,
				1,
				7.822,
				0.486,
				7.844,
				0.832,
				7.867,
				1,
				0,
				8,
				1,
				1,
				8.022,
				0.878,
				8.044,
				0.519,
				8.067,
				0.541,
				0,
				8.133,
				0.541,
				1,
				8.167,
				0.481,
				8.2,
				1.033,
				8.233,
				1,
				0,
				8.467,
				1,
				2,
				8.5,
				0.933,
				1,
				8.556,
				0.473,
				8.611,
				-0.005,
				8.667,
				0,
				0,
				10.933,
				0,
				0,
				10.967,
				0
			]
		},
		{
			"Target": "Parameter",
			"Id": "PARAM_MOUTH_SIZE_X",
			"Segments": [
				0,
				0,
				1,
				1.244,
				0,
				2.489,
				0,
				3.733,
				0,
				1,
				3.867,
				0,
				4,
				0.36,
				4.133,
				0.36,
				1,
				6.089,
				0.36,
				8.044,
				0.36,
				10,
				0.36,
				1,
				10.067,
				0.36,
				10.133,
				0,
				10.2,
				0,
				1,
				10.456,
				0,
				10.711,
				0,
				10.967,
				0
			]
		},
		{
			"Target": "Parameter",
			"Id": "PARAM_MOUTH_SIZE_Y",
			"Segments": [
				0,
				0,
				1,
				1.244,
				0,
				2.489,
				0,
				3.733,
				0,
				1,
				3.867,
				0,
				4,
				-0.13,
				4.133,
				-0.13,
				1,
				6.089,
				-0.13,
				8.044,
				-0.13,
				10,
				-0.13,
				1,
				10.067,
				-0.13,
				10.133,
				0,
				10.2,
				0,
				1,
				10.456,
				0,
				10.711,
				0,
				10.967,
				0
			]
		},
		{
			"Target": "Parameter",
			"Id": "PARAM_CHEEK",
			"Segments": [
				0,
				0,
				1,
				0.144,
				0,
				0.289,
				0,
				0.433,
				0,
				1,
				0.956,
				0,
				1.478,
				0.17,
				2,
				0.17,
				1,
				4.667,
				0.17,
				7.333,
				0.17,
				10,
				0.17,
				1,
				10.322,
				0.17,
				10.644,
				0,
				10.967,
				0
			]
		},
		{
			"Target": "Parameter",
			"Id": "PARAM_BREATH",
			"Segments": [
				0,
				0,
				1,
				0.111,
				0,
				0.222,
				0.56,
				0.333,
				0.56,
				1,
				0.456,
				0.56,
				0.578,
				0.09,
				0.7,
				0.09,
				1,
				0.956,
				0.09,
				1.211,
				0.21,
				1.467,
				0.21,
				1,
				1.611,
				0.21,
				1.756,
				0,
				1.9,
				0,
				1,
				2.244,
				0,
				2.589,
				0,
				2.933,
				0,
				1,
				3.222,
				0,
				3.511,
				0.016,
				3.8,
				0.18,
				1,
				3.933,
				0.256,
				4.067,
				0.75,
				4.2,
				0.75,
				1,
				4.333,
				0.75,
				4.467,
				0,
				4.6,
				0,
				1,
				4.8,
				0,
				5,
				0.2,
				5.2,
				0.2,
				1,
				5.333,
				0.2,
				5.467,
				0,
				5.6,
				0,
				1,
				5.778,
				0,
				5.956,
				0.119,
				6.133,
				0.21,
				1,
				6.244,
				0.267,
				6.356,
				0.27,
				6.467,
				0.32,
				1,
				6.556,
				0.36,
				6.644,
				0.43,
				6.733,
				0.43,
				1,
				7.044,
				0.43,
				7.356,
				0.14,
				7.667,
				0.14,
				1,
				7.844,
				0.14,
				8.022,
				0.32,
				8.2,
				0.32,
				1,
				8.389,
				0.32,
				8.578,
				0,
				8.767,
				0,
				1,
				8.978,
				0,
				9.189,
				0.21,
				9.4,
				0.21,
				1,
				9.6,
				0.21,
				9.8,
				0.21,
				10,
				0.21,
				1,
				10.144,
				0.21,
				10.289,
				0.54,
				10.433,
				0.54,
				1,
				10.611,
				0.54,
				10.789,
				0,
				10.967,
				0
			]
		},
		{
			"Target": "Parameter",
			"Id": "PARAM_X_ALL",
			"Segments": [
				0,
				0,
				1,
				0.489,
				0,
				0.978,
				0,
				1.467,
				0,
				1,
				1.611,
				0,
				1.756,
				0,
				1.9,
				0,
				1,
				2.244,
				0,
				2.589,
				0,
				2.933,
				0,
				1,
				3.222,
				0,
				3.511,
				0,
				3.8,
				0,
				1,
				4.267,
				0,
				4.733,
				0,
				5.2,
				0,
				1,
				5.333,
				0,
				5.467,
				0.09,
				5.6,
				0.09,
				1,
				5.778,
				0.09,
				5.956,
				0.09,
				6.133,
				0.09,
				1,
				6.333,
				0.09,
				6.533,
				0.091,
				6.733,
				0.11,
				1,
				6.867,
				0.123,
				7,
				0.16,
				7.133,
				0.16,
				1,
				7.311,
				0.16,
				7.489,
				0.16,
				7.667,
				0.16,
				1,
				7.844,
				0.16,
				8.022,
				0.16,
				8.2,
				0.16,
				1,
				8.6,
				0.16,
				9,
				0.16,
				9.4,
				0.16,
				1,
				9.6,
				0.16,
				9.8,
				0.16,
				10,
				0.16,
				1,
				10.2,
				0.16,
				10.4,
				0,
				10.6,
				0,
				1,
				10.722,
				0,
				10.844,
				0,
				10.967,
				0
			]
		},
		{
			"Target": "Parameter",
			"Id": "PARAM_Y_ALL",
			"Segments": [
				0,
				0,
				1,
				0.489,
				0,
				0.978,
				0,
				1.467,
				0,
				1,
				1.611,
				0,
				1.756,
				0,
				1.9,
				0,
				1,
				2.244,
				0,
				2.589,
				0,
				2.933,
				0,
				1,
				3.222,
				0,
				3.511,
				0,
				3.8,
				0,
				1,
				4.267,
				0,
				4.733,
				0,
				5.2,
				0,
				1,
				5.511,
				0,
				5.822,
				0,
				6.133,
				0,
				1,
				7.222,
				0,
				8.311,
				0,
				9.4,
				0,
				1,
				9.6,
				0,
				9.8,
				0,
				10,
				0,
				1,
				10.322,
				0,
				10.644,
				0,
				10.967,
				0
			]
		},
		{
			"Target": "Parameter",
			"Id": "PARAM_Z_ALL",
			"Segments": [
				0,
				0,
				1,
				0.489,
				0,
				0.978,
				0,
				1.467,
				0,
				1,
				1.611,
				0,
				1.756,
				0,
				1.9,
				0,
				1,
				2.244,
				0,
				2.589,
				0,
				2.933,
				0,
				1,
				3.222,
				0,
				3.511,
				0,
				3.8,
				0,
				1,
				4.267,
				0,
				4.733,
				0,
				5.2,
				0,
				1,
				5.511,
				0,
				5.822,
				0,
				6.133,
				0,
				1,
				6.333,
				0,
				6.533,
				0,
				6.733,
				0,
				1,
				6.867,
				0,
				7,
				0.02,
				7.133,
				0.02,
				1,
				7.311,
				0.02,
				7.489,
				0.02,
				7.667,
				0.02,
				1,
				7.844,
				0.02,
				8.022,
				0.02,
				8.2,
				0.02,
				1,
				8.6,
				0.02,
				9,
				0.02,
				9.4,
				0.02,
				1,
				9.6,
				0.02,
				9.8,
				0.02,
				10,
				0.02,
				1,
				10.2,
				0.02,
				10.4,
				0,
				10.6,
				0,
				1,
				10.722,
				0,
				10.844,
				0,
				10.967,
				0
			]
		},
		{
			"Target": "Parameter",
			"Id": "PARAM_SCALE_ALL",
			"Segments": [
				0,
				0,
				1,
				0.489,
				0,
				0.978,
				0,
				1.467,
				0,
				1,
				1.611,
				0,
				1.756,
				0,
				1.9,
				0,
				1,
				2.244,
				0,
				2.589,
				0,
				2.933,
				0,
				1,
				3.222,
				0,
				3.511,
				0,
				3.8,
				0,
				1,
				4.267,
				0,
				4.733,
				0,
				5.2,
				0,
				1,
				5.511,
				0,
				5.822,
				0,
				6.133,
				0,
				1,
				7.222,
				0,
				8.311,
				0,
				9.4,
				0,
				1,
				9.6,
				0,
				9.8,
				0,
				10,
				0,
				1,
				10.322,
				0,
				10.644,
				0,
				10.967,
				0
			]
		},
		{
			"Target": "Parameter",
			"Id": "PARAM_SHOULDER_L",
			"Segments": [
				0,
				0,
				1,
				0.256,
				0,
				0.511,
				0.13,
				0.767,
				0.13,
				1,
				1.022,
				0.13,
				1.278,
				0.13,
				1.533,
				0.13,
				1,
				1.678,
				0.13,
				1.822,
				0.13,
				1.967,
				0.13,
				1,
				2.311,
				0.13,
				2.656,
				0,
				3,
				0,
				1,
				3.289,
				0,
				3.578,
				0.034,
				3.867,
				0.11,
				1,
				4.133,
				0.18,
				4.4,
				0.22,
				4.667,
				0.22,
				1,
				4.867,
				0.22,
				5.067,
				0.197,
				5.267,
				0.12,
				1,
				5.433,
				0.055,
				5.6,
				0,
				5.767,
				0,
				1,
				5.967,
				0,
				6.167,
				0,
				6.367,
				0,
				1,
				6.644,
				0,
				6.922,
				0,
				7.2,
				0,
				1,
				7.378,
				0,
				7.556,
				0,
				7.733,
				0,
				1,
				7.911,
				0,
				8.089,
				0,
				8.267,
				0,
				1,
				8.456,
				0,
				8.644,
				0.28,
				8.833,
				0.28,
				1,
				9.044,
				0.28,
				9.256,
				0.28,
				9.467,
				0.28,
				1,
				9.644,
				0.28,
				9.822,
				0.28,
				10,
				0.28,
				1,
				10.322,
				0.28,
				10.644,
				0,
				10.967,
				0
			]
		},
		{
			"Target": "Parameter",
			"Id": "PARAM_HAND_L_L",
			"Segments": [
				0,
				0,
				1,
				0.233,
				0,
				0.467,
				0.77,
				0.7,
				0.77,
				1,
				0.956,
				0.77,
				1.211,
				0.77,
				1.467,
				0.77,
				1,
				1.611,
				0.77,
				1.756,
				0.77,
				1.9,
				0.77,
				1,
				2.533,
				0.77,
				3.167,
				0.77,
				3.8,
				0.77,
				1,
				4.211,
				0.77,
				4.622,
				1,
				5.033,
				1,
				1,
				5.389,
				1,
				5.744,
				1,
				6.1,
				1,
				1,
				7.011,
				1,
				7.922,
				1,
				8.833,
				1,
				1,
				9.022,
				1,
				9.211,
				0.77,
				9.4,
				0.77,
				1,
				9.6,
				0.77,
				9.8,
				0.77,
				10,
				0.77,
				1,
				10.322,
				0.77,
				10.644,
				0,
				10.967,
				0
			]
		},
		{
			"Target": "Parameter",
			"Id": "PARAM_LAYER_ARM",
			"Segments": [
				0,
				0,
				1,
				0.111,
				0,
				0.222,
				0,
				0.333,
				0,
				2,
				0.367,
				1,
				2,
				4.433,
				0,
				2,
				4.467,
				0,
				2,
				10.967,
				0
			]
		},
		{
			"Target": "Parameter",
			"Id": "PARAM_zuodbtoushi",
			"Segments": [
				0,
				0,
				1,
				0.267,
				0,
				0.533,
				0,
				0.8,
				0,
				1,
				1.7,
				0,
				2.6,
				0.2,
				3.5,
				0.2,
				1,
				4.011,
				0.2,
				4.522,
				0,
				5.033,
				0,
				1,
				6.344,
				0,
				7.656,
				0,
				8.967,
				0,
				1,
				9.633,
				0,
				10.3,
				0,
				10.967,
				0
			]
		},
		{
			"Target": "Parameter",
			"Id": "PARAM_zuoxbtoushi",
			"Segments": [
				0,
				0,
				1,
				0.267,
				0,
				0.533,
				0,
				0.8,
				0,
				1,
				1.7,
				0,
				2.6,
				-1,
				3.5,
				-1,
				1,
				4.011,
				-1,
				4.522,
				0,
				5.033,
				0,
				1,
				6.344,
				0,
				7.656,
				0,
				8.967,
				0,
				1,
				9.633,
				0,
				10.3,
				0,
				10.967,
				0
			]
		},
		{
			"Target": "Parameter",
			"Id": "PARAM_ARM_L",
			"Segments": [
				0,
				0,
				1,
				0.267,
				0,
				0.533,
				-28.144,
				0.8,
				-30,
				1,
				1.944,
				-37.964,
				3.089,
				-40,
				4.233,
				-40,
				1,
				4.5,
				-40,
				4.767,
				-20.93,
				5.033,
				-20,
				1,
				5.989,
				-16.667,
				6.944,
				-16,
				7.9,
				-16,
				1,
				8.256,
				-16,
				8.611,
				-20,
				8.967,
				-20,
				1,
				9.633,
				-20,
				10.3,
				0,
				10.967,
				0
			]
		},
		{
			"Target": "Parameter",
			"Id": "PARAM_LOWARM_L",
			"Segments": [
				0,
				0,
				1,
				0.267,
				0,
				0.533,
				34,
				0.8,
				34,
				1,
				1.944,
				34,
				3.089,
				33.242,
				4.233,
				30,
				1,
				4.5,
				29.245,
				4.767,
				0,
				5.033,
				0,
				1,
				5.989,
				0,
				6.944,
				2,
				7.9,
				2,
				1,
				8.256,
				2,
				8.611,
				0,
				8.967,
				0,
				1,
				9.633,
				0,
				10.3,
				0,
				10.967,
				0
			]
		},
		{
			"Target": "Parameter",
			"Id": "PARAM_zuowan",
			"Segments": [
				0,
				0,
				1,
				0.267,
				0,
				0.533,
				-0.019,
				0.8,
				-0.1,
				1,
				1.167,
				-0.212,
				1.533,
				-0.3,
				1.9,
				-0.3,
				1,
				2.433,
				-0.3,
				2.967,
				-0.018,
				3.5,
				0.1,
				1,
				3.8,
				0.166,
				4.1,
				0.145,
				4.4,
				0.2,
				1,
				4.611,
				0.238,
				4.822,
				0.8,
				5.033,
				0.8,
				1,
				5.989,
				0.8,
				6.944,
				0.775,
				7.9,
				0.6,
				1,
				8.256,
				0.535,
				8.611,
				0,
				8.967,
				0,
				1,
				9.633,
				0,
				10.3,
				0,
				10.967,
				0
			]
		},
		{
			"Target": "Parameter",
			"Id": "PARAM_HAND_L",
			"Segments": [
				0,
				0,
				1,
				0.267,
				0,
				0.533,
				0.039,
				0.8,
				0.1,
				1,
				1.7,
				0.305,
				2.6,
				0.4,
				3.5,
				0.4,
				1,
				4.256,
				0.4,
				5.011,
				-0.6,
				5.767,
				-0.6,
				1,
				6.833,
				-0.6,
				7.9,
				0,
				8.967,
				0,
				1,
				9.633,
				0,
				10.3,
				0,
				10.967,
				0
			]
		},
		{
			"Target": "Parameter",
			"Id": "PARAM_HAND_L_2",
			"Segments": [
				0,
				0,
				1,
				3.656,
				0,
				7.311,
				0,
				10.967,
				0
			]
		},
		{
			"Target": "Parameter",
			"Id": "PARAM_SHOULDER_R",
			"Segments": [
				0,
				0,
				1,
				0.267,
				0,
				0.533,
				0.41,
				0.8,
				0.41,
				1,
				1.222,
				0.41,
				1.644,
				-0.5,
				2.067,
				-0.5,
				1,
				2.389,
				-0.5,
				2.711,
				0.21,
				3.033,
				0.21,
				1,
				3.322,
				0.21,
				3.611,
				0.21,
				3.9,
				0.21,
				1,
				4.133,
				0.21,
				4.367,
				0.08,
				4.6,
				0.08,
				1,
				4.833,
				0.08,
				5.067,
				0.13,
				5.3,
				0.13,
				1,
				5.433,
				0.13,
				5.567,
				0.08,
				5.7,
				0.08,
				1,
				5.933,
				0.08,
				6.167,
				0.08,
				6.4,
				0.08,
				1,
				7.433,
				0.08,
				8.467,
				0,
				9.5,
				0,
				1,
				9.667,
				0,
				9.833,
				0,
				10,
				0,
				1,
				10.322,
				0,
				10.644,
				0,
				10.967,
				0
			]
		},
		{
			"Target": "Parameter",
			"Id": "PARAM_HAND_R_L",
			"Segments": [
				0,
				0,
				1,
				1.267,
				0,
				2.533,
				0,
				3.8,
				0,
				1,
				4.033,
				0,
				4.267,
				1,
				4.5,
				1,
				1,
				6.133,
				1,
				7.767,
				1,
				9.4,
				1,
				1,
				9.6,
				1,
				9.8,
				1,
				10,
				1,
				1,
				10.2,
				1,
				10.4,
				0.989,
				10.6,
				0.75,
				1,
				10.722,
				0.604,
				10.844,
				0,
				10.967,
				0
			]
		},
		{
			"Target": "Parameter",
			"Id": "PARAM_youdbtoushi1",
			"Segments": [
				0,
				0,
				1,
				1.267,
				0,
				2.533,
				0,
				3.8,
				0,
				1,
				5.667,
				0,
				7.533,
				0,
				9.4,
				0,
				1,
				9.6,
				0,
				9.8,
				0,
				10,
				0,
				1,
				10.322,
				0,
				10.644,
				0,
				10.967,
				0
			]
		},
		{
			"Target": "Parameter",
			"Id": "PARAM_R_ARM",
			"Segments": [
				0,
				0,
				1,
				0.244,
				0,
				0.489,
				0,
				0.733,
				0,
				1,
				1.178,
				0,
				1.622,
				-0.6,
				2.067,
				-0.6,
				1,
				2.644,
				-0.6,
				3.222,
				0,
				3.8,
				0,
				1,
				5.667,
				0,
				7.533,
				0,
				9.4,
				0,
				1,
				9.6,
				0,
				9.8,
				0,
				10,
				0,
				1,
				10.322,
				0,
				10.644,
				0,
				10.967,
				0
			]
		},
		{
			"Target": "Parameter",
			"Id": "PARAM_ARM_R",
			"Segments": [
				0,
				0,
				1,
				0.244,
				0,
				0.489,
				4,
				0.733,
				4,
				1,
				1.178,
				4,
				1.622,
				-11,
				2.067,
				-11,
				1,
				2.378,
				-11,
				2.689,
				1.422,
				3,
				5,
				1,
				3.289,
				8.323,
				3.578,
				8,
				3.867,
				8,
				1,
				4.2,
				8,
				4.533,
				-5,
				4.867,
				-5,
				1,
				5.2,
				-5,
				5.533,
				5,
				5.867,
				5,
				1,
				6.411,
				5,
				6.956,
				-5,
				7.5,
				-5,
				1,
				7.678,
				-5,
				7.856,
				11,
				8.033,
				11,
				1,
				8.3,
				11,
				8.567,
				-8,
				8.833,
				-8,
				1,
				9.544,
				-8,
				10.256,
				0,
				10.967,
				0
			]
		},
		{
			"Target": "Parameter",
			"Id": "PARAM_LOWARM_R",
			"Segments": [
				0,
				0,
				1,
				0.289,
				0,
				0.489,
				-9,
				0.733,
				-9,
				1,
				0.778,
				-9,
				1.622,
				20,
				2.067,
				20,
				1,
				2.411,
				20,
				2.656,
				-6.834,
				3,
				-6,
				1,
				3.322,
				-6,
				3.644,
				-6.079,
				3.967,
				-3,
				1,
				4.267,
				-0.134,
				4.567,
				18.453,
				4.867,
				19,
				1,
				5.2,
				19.607,
				5.533,
				19.308,
				5.867,
				20,
				1,
				6.411,
				21.13,
				6.956,
				25,
				7.5,
				25,
				1,
				7.678,
				25,
				7.856,
				-4,
				8.033,
				-4,
				1,
				8.3,
				-4,
				8.567,
				0,
				8.833,
				0,
				1,
				9.544,
				0,
				10.656,
				0,
				10.967,
				0
			]
		},
		{
			"Target": "Parameter",
			"Id": "PARAM_youwan",
			"Segments": [
				0,
				-0.55,
				1,
				0.111,
				-0.55,
				0.222,
				0.134,
				0.333,
				0.17,
				1,
				0.467,
				0.33,
				0.6,
				0.32,
				0.733,
				0.32,
				1,
				1.178,
				0.32,
				1.622,
				-0.3,
				2.067,
				-0.3,
				1,
				2.378,
				-0.3,
				2.689,
				0.27,
				3,
				0.27,
				1,
				3.356,
				0.27,
				3.711,
				0.09,
				4.067,
				0.09,
				1,
				4.333,
				0.09,
				4.6,
				1.751,
				4.867,
				1.87,
				1,
				5.2,
				2.019,
				5.533,
				2,
				5.867,
				2,
				1,
				6.411,
				2,
				6.956,
				2.034,
				7.5,
				1.87,
				1,
				8.033,
				1.71,
				8.567,
				-0.7,
				9.1,
				-0.7,
				1,
				9.722,
				-0.7,
				10.744,
				-0.55,
				10.967,
				-0.55
			]
		},
		{
			"Target": "Parameter",
			"Id": "PARAM_HAND_R",
			"Segments": [
				0,
				0,
				1,
				0.111,
				0,
				0.222,
				0.2,
				0.333,
				0.2,
				1,
				0.467,
				0.2,
				0.6,
				0.048,
				0.733,
				0,
				1,
				1.178,
				-0.159,
				1.622,
				-0.2,
				2.067,
				-0.2,
				1,
				2.378,
				-0.2,
				2.689,
				0,
				3,
				0,
				1,
				3.378,
				0,
				3.756,
				-0.068,
				4.133,
				-0.28,
				1,
				4.378,
				-0.417,
				4.622,
				-0.54,
				4.867,
				-0.54,
				1,
				5.744,
				-0.54,
				6.622,
				-0.54,
				7.5,
				-0.54,
				1,
				8.656,
				-0.54,
				9.811,
				0,
				10.967,
				0
			]
		},
		{
			"Target": "Parameter",
			"Id": "PARAM_HAND_R_VIS1",
			"Segments": [
				0,
				1,
				1,
				1.456,
				1,
				2.911,
				1,
				4.367,
				1,
				2,
				4.4,
				0,
				2,
				7.7,
				0,
				2,
				7.733,
				1,
				2,
				10.967,
				1
			]
		},
		{
			"Target": "Parameter",
			"Id": "PARAM_HAND_R_VIS2",
			"Segments": [
				0,
				0,
				1,
				1.456,
				0,
				2.911,
				0,
				4.367,
				0,
				2,
				4.4,
				1,
				2,
				7.7,
				1,
				2,
				7.733,
				0,
				2,
				10.967,
				0
			]
		},
		{
			"Target": "Parameter",
			"Id": "PARAM_FAN_X",
			"Segments": [
				0,
				0,
				1,
				3.656,
				0,
				7.311,
				0,
				10.967,
				0
			]
		},
		{
			"Target": "Parameter",
			"Id": "PARAM_FAN_Y",
			"Segments": [
				0,
				0,
				1,
				3.656,
				0,
				7.311,
				0,
				10.967,
				0
			]
		},
		{
			"Target": "Parameter",
			"Id": "PARAM_FAN_Z",
			"Segments": [
				0,
				0,
				1,
				3.656,
				0,
				7.311,
				0,
				10.967,
				0
			]
		},
		{
			"Target": "Parameter",
			"Id": "PARAM_FAN_TURN",
			"Segments": [
				0,
				0,
				1,
				1.267,
				0,
				2.533,
				0,
				3.8,
				0,
				1,
				4.156,
				0,
				4.511,
				1,
				4.867,
				1,
				1,
				5.744,
				1,
				6.622,
				1,
				7.5,
				1,
				1,
				8.078,
				1,
				8.656,
				0,
				9.233,
				0,
				1,
				9.811,
				0,
				10.389,
				0,
				10.967,
				0
			]
		},
		{
			"Target": "Parameter",
			"Id": "PARAM_FAN_WOOL",
			"Segments": [
				0,
				0,
				1,
				0.122,
				-0.212,
				0.333,
				-0.6,
				0.5,
				-0.6,
				1,
				0.722,
				-0.6,
				0.944,
				0.7,
				1.167,
				0.7,
				1,
				1.4,
				0.7,
				1.633,
				-0.6,
				1.867,
				-0.6,
				1,
				2.089,
				-0.6,
				2.311,
				0.6,
				2.533,
				0.6,
				1,
				2.789,
				0.6,
				3.044,
				-0.7,
				3.3,
				-0.7,
				1,
				3.567,
				-0.7,
				3.833,
				0.7,
				4.1,
				0.7,
				1,
				4.389,
				0.7,
				4.678,
				-0.9,
				4.967,
				-0.9,
				1,
				5.244,
				-0.9,
				5.522,
				0.5,
				5.8,
				0.5,
				1,
				6.089,
				0.5,
				6.378,
				-0.6,
				6.667,
				-0.6,
				1,
				6.978,
				-0.6,
				7.289,
				0.8,
				7.6,
				0.8,
				1,
				7.867,
				0.8,
				8.133,
				-0.7,
				8.4,
				-0.7,
				1,
				8.678,
				-0.7,
				8.956,
				0.6,
				9.233,
				0.6,
				1,
				9.544,
				0.6,
				9.856,
				-0.5,
				10.167,
				-0.5,
				1,
				10.433,
				-0.5,
				10.744,
				-0.206,
				10.967,
				0
			]
		},
		{
			"Target": "Parameter",
			"Id": "PARAM_FAN_WOOL_F",
			"Segments": [
				0,
				0,
				1,
				0.208,
				-0.231,
				0.511,
				-0.6,
				0.767,
				-0.6,
				1,
				0.978,
				-0.6,
				1.189,
				1,
				1.4,
				1,
				1,
				1.622,
				1,
				1.844,
				-0.6,
				2.067,
				-0.6,
				1,
				2.278,
				-0.6,
				2.489,
				0.6,
				2.7,
				0.6,
				1,
				2.989,
				0.6,
				3.278,
				-0.9,
				3.567,
				-0.9,
				1,
				3.8,
				-0.9,
				4.033,
				0.1,
				4.267,
				0.1,
				1,
				4.644,
				0.1,
				5.022,
				0.063,
				5.4,
				-0.2,
				1,
				5.667,
				-0.385,
				5.933,
				-0.7,
				6.2,
				-0.7,
				1,
				6.467,
				-0.7,
				6.733,
				0.5,
				7,
				0.5,
				1,
				7.289,
				0.5,
				7.578,
				0.3,
				7.867,
				-0.1,
				1,
				8.156,
				-0.5,
				8.444,
				-0.7,
				8.733,
				-0.7,
				1,
				9.033,
				-0.7,
				9.333,
				0.2,
				9.633,
				0.2,
				1,
				10.078,
				0.2,
				10.542,
				0.094,
				10.967,
				0
			]
		},
		{
			"Target": "Parameter",
			"Id": "Param2",
			"Segments": [
				0,
				0,
				1,
				0.183,
				-0.342,
				0.511,
				-1,
				0.767,
				-1,
				1,
				0.978,
				-1,
				1.189,
				0.9,
				1.4,
				0.9,
				1,
				1.622,
				0.9,
				1.844,
				-0.5,
				2.067,
				-0.5,
				1,
				2.278,
				-0.5,
				2.489,
				0.5,
				2.7,
				0.5,
				1,
				2.989,
				0.5,
				3.278,
				-1,
				3.567,
				-1,
				1,
				3.8,
				-1,
				4.033,
				0.6,
				4.267,
				0.6,
				1,
				4.644,
				0.6,
				5.022,
				-0.5,
				5.4,
				-0.5,
				1,
				5.667,
				-0.5,
				5.933,
				0.1,
				6.2,
				0.1,
				1,
				6.467,
				0.1,
				6.733,
				-1,
				7,
				-1,
				1,
				7.289,
				-1,
				7.578,
				0.7,
				7.867,
				0.7,
				1,
				8.156,
				0.7,
				8.444,
				-0.9,
				8.733,
				-0.9,
				1,
				9.033,
				-0.9,
				9.333,
				0.7,
				9.633,
				0.7,
				1,
				9.933,
				0.7,
				10.233,
				-0.4,
				10.533,
				-0.4,
				1,
				10.678,
				-0.4,
				10.833,
				-0.192,
				10.967,
				0
			]
		},
		{
			"Target": "Parameter",
			"Id": "PARAM_RUYAO_X",
			"Segments": [
				0,
				0,
				1,
				0.117,
				0.246,
				0.289,
				0.6,
				0.433,
				0.6,
				1,
				0.7,
				0.6,
				0.967,
				-0.5,
				1.233,
				-0.5,
				1,
				1.511,
				-0.5,
				1.789,
				0.4,
				2.067,
				0.4,
				1,
				2.311,
				0.4,
				2.556,
				-0.3,
				2.8,
				-0.3,
				1,
				3.144,
				-0.3,
				3.489,
				0.5,
				3.833,
				0.5,
				1,
				4.133,
				0.5,
				4.433,
				-0.4,
				4.733,
				-0.4,
				1,
				5.078,
				-0.4,
				5.422,
				0.8,
				5.767,
				0.8,
				1,
				6.633,
				0.8,
				6.344,
				-0.4,
				6.633,
				-0.4,
				1,
				6.878,
				-0.4,
				7.122,
				0.6,
				7.367,
				0.6,
				1,
				7.656,
				0.6,
				7.944,
				-0.6,
				8.233,
				-0.6,
				1,
				8.533,
				-0.6,
				8.833,
				0.6,
				9.133,
				0.6,
				1,
				9.433,
				0.6,
				9.733,
				-0.5,
				10.033,
				-0.5,
				1,
				10.344,
				-0.5,
				10.675,
				-0.227,
				10.967,
				0
			]
		},
		{
			"Target": "Parameter",
			"Id": "PARAM_RUYAO_Y",
			"Segments": [
				0,
				0,
				1,
				0.2,
				0.162,
				0.489,
				0.4,
				0.733,
				0.4,
				1,
				0.956,
				0.4,
				1.178,
				-0.3,
				1.4,
				-0.3,
				1,
				1.644,
				-0.3,
				1.889,
				0.5,
				2.133,
				0.5,
				1,
				2.378,
				0.5,
				2.622,
				-0.4,
				2.867,
				-0.4,
				1,
				3.133,
				-0.4,
				3.4,
				0.4,
				3.667,
				0.4,
				1,
				3.811,
				0.4,
				3.956,
				-0.2,
				4.1,
				-0.2,
				1,
				4.2,
				-0.2,
				4.3,
				0.3,
				4.4,
				0.3,
				1,
				4.589,
				0.3,
				4.778,
				-0.3,
				4.967,
				-0.3,
				1,
				5.233,
				-0.3,
				5.5,
				0.3,
				5.767,
				0.3,
				1,
				6.056,
				0.3,
				6.344,
				-0.3,
				6.633,
				-0.3,
				1,
				6.933,
				-0.3,
				7.233,
				0.5,
				7.533,
				0.5,
				1,
				7.778,
				0.5,
				8.022,
				-0.1,
				8.267,
				-0.1,
				1,
				8.478,
				-0.1,
				8.689,
				0.6,
				8.9,
				0.6,
				1,
				9.2,
				0.6,
				9.5,
				-0.2,
				9.8,
				-0.2,
				1,
				10,
				-0.2,
				10.2,
				0.1,
				10.4,
				0.1,
				1,
				10.589,
				0.1,
				10.758,
				0.045,
				10.967,
				0
			]
		},
		{
			"Target": "Parameter",
			"Id": "PARAM_L_THIGH",
			"Segments": [
				0,
				0,
				1,
				0.111,
				0,
				0.222,
				-0.09,
				0.333,
				-0.09,
				1,
				0.5,
				-0.09,
				0.667,
				0.01,
				0.833,
				0.01,
				1,
				1.533,
				0.01,
				2.233,
				-0.02,
				2.933,
				-0.02,
				1,
				3.222,
				-0.02,
				3.511,
				-0.022,
				3.8,
				0.01,
				1,
				4.067,
				0.039,
				4.333,
				0.13,
				4.6,
				0.13,
				1,
				4.8,
				0.13,
				5,
				0.13,
				5.2,
				0.13,
				1,
				5.333,
				0.13,
				5.467,
				0.09,
				5.6,
				0.09,
				1,
				5.778,
				0.09,
				5.956,
				0.09,
				6.133,
				0.09,
				1,
				6.333,
				0.09,
				6.533,
				0.03,
				6.733,
				0.03,
				1,
				7.822,
				0.03,
				8.911,
				0.03,
				10,
				0.03,
				1,
				10.322,
				0.03,
				10.644,
				0,
				10.967,
				0
			]
		},
		{
			"Target": "Parameter",
			"Id": "PARAM_L_CRUS",
			"Segments": [
				0,
				0,
				1,
				0.144,
				0,
				0.289,
				-0.01,
				0.433,
				-0.01,
				1,
				0.6,
				-0.01,
				0.767,
				-0.01,
				0.933,
				-0.01,
				1,
				1.144,
				-0.01,
				1.356,
				-0.03,
				1.567,
				-0.03,
				1,
				1.711,
				-0.03,
				1.856,
				-0.03,
				2,
				-0.03,
				1,
				2.344,
				-0.03,
				2.689,
				-0.06,
				3.033,
				-0.06,
				1,
				3.322,
				-0.06,
				3.611,
				0,
				3.9,
				0,
				1,
				4.367,
				0,
				4.833,
				0,
				5.3,
				0,
				1,
				5.433,
				0,
				5.567,
				0.02,
				5.7,
				0.02,
				1,
				5.878,
				0.02,
				6.056,
				0.02,
				6.233,
				0.02,
				1,
				7.489,
				0.02,
				8.744,
				0.02,
				10,
				0.02,
				1,
				10.322,
				0.02,
				10.644,
				0,
				10.967,
				0
			]
		},
		{
			"Target": "Parameter",
			"Id": "PARAM_L_FOOT",
			"Segments": [
				0,
				0,
				1,
				0.144,
				0,
				0.289,
				0,
				0.433,
				0,
				1,
				0.6,
				0,
				0.767,
				0,
				0.933,
				0,
				1,
				1.144,
				0,
				1.356,
				0.01,
				1.567,
				0.01,
				1,
				1.711,
				0.01,
				1.856,
				0.01,
				2,
				0.01,
				1,
				2.344,
				0.01,
				2.689,
				0.01,
				3.033,
				0.01,
				1,
				3.322,
				0.01,
				3.611,
				0.02,
				3.9,
				0.02,
				1,
				4.367,
				0.02,
				4.833,
				0.01,
				5.3,
				0.01,
				1,
				6.867,
				0.01,
				8.433,
				0.01,
				10,
				0.01,
				1,
				10.322,
				0.01,
				10.644,
				0,
				10.967,
				0
			]
		},
		{
			"Target": "Parameter",
			"Id": "PARAM_L_FOOTPAIN",
			"Segments": [
				0,
				0,
				1,
				0.144,
				0,
				0.289,
				0,
				0.433,
				0,
				1,
				0.6,
				0,
				0.767,
				0,
				0.933,
				0,
				1,
				1.922,
				0,
				2.911,
				0,
				3.9,
				0,
				1,
				4.367,
				0,
				4.833,
				0,
				5.3,
				0,
				1,
				6.867,
				0,
				8.433,
				0,
				10,
				0,
				1,
				10.322,
				0,
				10.644,
				0,
				10.967,
				0
			]
		},
		{
			"Target": "Parameter",
			"Id": "PARAM_R_THIGH",
			"Segments": [
				0,
				0,
				1,
				0.111,
				0,
				0.222,
				-0.047,
				0.333,
				-0.11,
				1,
				0.5,
				-0.205,
				0.667,
				-0.24,
				0.833,
				-0.24,
				1,
				1.044,
				-0.24,
				1.256,
				-0.22,
				1.467,
				-0.22,
				1,
				1.611,
				-0.22,
				1.756,
				-0.22,
				1.9,
				-0.22,
				1,
				2.244,
				-0.22,
				2.589,
				-0.227,
				2.933,
				-0.24,
				1,
				3.222,
				-0.251,
				3.511,
				-0.253,
				3.8,
				-0.27,
				1,
				4.067,
				-0.285,
				4.333,
				-0.35,
				4.6,
				-0.35,
				1,
				4.8,
				-0.35,
				5,
				-0.35,
				5.2,
				-0.33,
				1,
				5.333,
				-0.317,
				5.467,
				-0.25,
				5.6,
				-0.25,
				1,
				5.778,
				-0.25,
				5.956,
				-0.25,
				6.133,
				-0.25,
				1,
				6.333,
				-0.25,
				6.533,
				-0.118,
				6.733,
				-0.1,
				1,
				7.222,
				-0.056,
				7.711,
				-0.05,
				8.2,
				-0.05,
				1,
				8.389,
				-0.05,
				8.578,
				-0.11,
				8.767,
				-0.11,
				1,
				8.978,
				-0.11,
				9.189,
				-0.11,
				9.4,
				-0.11,
				1,
				9.6,
				-0.11,
				9.8,
				-0.11,
				10,
				-0.11,
				1,
				10.322,
				-0.11,
				10.644,
				0,
				10.967,
				0
			]
		},
		{
			"Target": "Parameter",
			"Id": "PARAM_R_CRUS",
			"Segments": [
				0,
				0,
				1,
				0.3,
				0,
				0.6,
				-0.21,
				0.9,
				-0.21,
				1,
				1.111,
				-0.21,
				1.322,
				-0.19,
				1.533,
				-0.19,
				1,
				1.678,
				-0.19,
				1.822,
				-0.19,
				1.967,
				-0.19,
				1,
				2.311,
				-0.19,
				2.656,
				-0.16,
				3,
				-0.16,
				1,
				3.289,
				-0.16,
				3.578,
				-0.165,
				3.867,
				-0.18,
				1,
				4.133,
				-0.194,
				4.4,
				-0.213,
				4.667,
				-0.23,
				1,
				4.867,
				-0.243,
				5.067,
				-0.25,
				5.267,
				-0.25,
				1,
				5.4,
				-0.25,
				5.533,
				-0.18,
				5.667,
				-0.18,
				1,
				5.844,
				-0.18,
				6.022,
				-0.18,
				6.2,
				-0.18,
				1,
				6.4,
				-0.18,
				6.6,
				-0.21,
				6.8,
				-0.21,
				1,
				7.289,
				-0.21,
				7.778,
				-0.18,
				8.267,
				-0.18,
				1,
				8.456,
				-0.18,
				8.644,
				-0.26,
				8.833,
				-0.26,
				1,
				9.044,
				-0.26,
				9.256,
				-0.26,
				9.467,
				-0.26,
				1,
				9.644,
				-0.26,
				9.822,
				-0.26,
				10,
				-0.26,
				1,
				10.322,
				-0.26,
				10.644,
				0,
				10.967,
				0
			]
		},
		{
			"Target": "Parameter",
			"Id": "PARAM_R_LAG_X",
			"Segments": [
				0,
				0,
				1,
				0.111,
				0,
				0.222,
				-0.29,
				0.333,
				-0.29,
				1,
				0.5,
				-0.29,
				0.667,
				-0.255,
				0.833,
				-0.24,
				1,
				1.533,
				-0.176,
				2.233,
				-0.143,
				2.933,
				-0.07,
				1,
				3.222,
				-0.04,
				3.511,
				0.09,
				3.8,
				0.09,
				1,
				4.067,
				0.09,
				4.333,
				-0.02,
				4.6,
				-0.02,
				1,
				4.8,
				-0.02,
				5,
				-0.02,
				5.2,
				-0.02,
				1,
				5.333,
				-0.02,
				5.467,
				0.5,
				5.6,
				0.5,
				1,
				5.778,
				0.5,
				5.956,
				0.44,
				6.133,
				0.44,
				1,
				6.822,
				0.44,
				7.511,
				0.44,
				8.2,
				0.44,
				1,
				8.389,
				0.44,
				8.578,
				-0.01,
				8.767,
				-0.01,
				1,
				8.978,
				-0.01,
				9.189,
				-0.01,
				9.4,
				-0.01,
				1,
				9.6,
				-0.01,
				9.8,
				-0.01,
				10,
				-0.01,
				1,
				10.322,
				-0.01,
				10.644,
				0,
				10.967,
				0
			]
		},
		{
			"Target": "Parameter",
			"Id": "PARAM_R_LAG_Y",
			"Segments": [
				0,
				0,
				1,
				0.111,
				0,
				0.222,
				0.32,
				0.333,
				0.32,
				1,
				0.5,
				0.32,
				0.667,
				-0.08,
				0.833,
				-0.08,
				1,
				1.822,
				-0.08,
				2.811,
				-0.08,
				3.8,
				-0.08,
				1,
				4.067,
				-0.08,
				4.333,
				0.08,
				4.6,
				0.08,
				1,
				4.8,
				0.08,
				5,
				0.08,
				5.2,
				0.08,
				1,
				5.367,
				0.08,
				5.533,
				0.41,
				5.7,
				0.41,
				1,
				6.533,
				0.41,
				7.367,
				0.325,
				8.2,
				0.08,
				1,
				8.389,
				0.024,
				8.578,
				-0.09,
				8.767,
				-0.09,
				1,
				9,
				-0.09,
				9.233,
				0.33,
				9.467,
				0.33,
				1,
				9.644,
				0.33,
				9.822,
				0.33,
				10,
				0.33,
				1,
				10.122,
				0.33,
				10.244,
				0.37,
				10.367,
				0.37,
				1,
				10.567,
				0.37,
				10.767,
				0,
				10.967,
				0
			]
		},
		{
			"Target": "Parameter",
			"Id": "PARAM_R_FOOT",
			"Segments": [
				0,
				0,
				1,
				0.144,
				0,
				0.289,
				-0.006,
				0.433,
				-0.04,
				1,
				0.6,
				-0.08,
				0.767,
				-0.177,
				0.933,
				-0.2,
				1,
				1.144,
				-0.229,
				1.356,
				-0.23,
				1.567,
				-0.23,
				1,
				1.711,
				-0.23,
				1.856,
				-0.23,
				2,
				-0.23,
				1,
				2.344,
				-0.23,
				2.689,
				-0.32,
				3.033,
				-0.32,
				1,
				3.322,
				-0.32,
				3.611,
				-0.21,
				3.9,
				-0.21,
				1,
				4.167,
				-0.21,
				4.433,
				-0.21,
				4.7,
				-0.21,
				1,
				4.9,
				-0.21,
				5.1,
				-0.196,
				5.3,
				-0.16,
				1,
				5.433,
				-0.136,
				5.567,
				-0.12,
				5.7,
				-0.12,
				1,
				5.878,
				-0.12,
				6.056,
				-0.12,
				6.233,
				-0.12,
				1,
				6.433,
				-0.12,
				6.633,
				-0.12,
				6.833,
				-0.12,
				1,
				7.322,
				-0.12,
				7.811,
				-0.08,
				8.3,
				-0.08,
				1,
				8.489,
				-0.08,
				8.678,
				-0.17,
				8.867,
				-0.17,
				1,
				9.244,
				-0.17,
				9.622,
				-0.17,
				10,
				-0.17,
				1,
				10.322,
				-0.17,
				10.644,
				0,
				10.967,
				0
			]
		},
		{
			"Target": "Parameter",
			"Id": "PARAM_R_FOOTPAIN",
			"Segments": [
				0,
				0,
				1,
				0.167,
				0,
				0.333,
				0.4,
				0.5,
				0.4,
				1,
				0.778,
				0.4,
				1.056,
				-0.5,
				1.333,
				-0.5,
				1,
				2.189,
				-0.5,
				3.044,
				0,
				3.9,
				0,
				1,
				4.367,
				0,
				4.833,
				-0.6,
				5.3,
				-0.6,
				1,
				5.611,
				-0.6,
				5.922,
				-0.1,
				6.233,
				-0.1,
				1,
				6.822,
				-0.1,
				7.411,
				-0.8,
				8,
				-0.8,
				1,
				8.533,
				-0.8,
				9.067,
				0.4,
				9.6,
				0.4,
				1,
				10.056,
				0.4,
				10.511,
				0,
				10.967,
				0
			]
		},
		{
			"Target": "Parameter",
			"Id": "PARAM_R_TOES",
			"Segments": [
				0,
				0,
				1,
				0.144,
				0,
				0.289,
				0.06,
				0.433,
				0.06,
				1,
				0.6,
				0.06,
				0.767,
				-0.048,
				0.933,
				-0.07,
				1,
				1.633,
				-0.164,
				2.333,
				-0.213,
				3.033,
				-0.31,
				1,
				3.322,
				-0.35,
				3.611,
				-0.43,
				3.9,
				-0.43,
				1,
				4.367,
				-0.43,
				4.833,
				-0.43,
				5.3,
				-0.43,
				1,
				5.611,
				-0.43,
				5.922,
				0.57,
				6.233,
				0.57,
				1,
				6.433,
				0.57,
				6.633,
				0.325,
				6.833,
				0.24,
				1,
				7.322,
				0.032,
				7.811,
				-0.01,
				8.3,
				-0.01,
				1,
				8.489,
				-0.01,
				8.678,
				0.154,
				8.867,
				0.23,
				1,
				9.244,
				0.382,
				9.622,
				0.41,
				10,
				0.41,
				1,
				10.322,
				0.41,
				10.644,
				0,
				10.967,
				0
			]
		},
		{
			"Target": "Parameter",
			"Id": "PARAM_HAIR_FRONT",
			"Segments": [
				0,
				0,
				1,
				0.117,
				-0.09,
				0.378,
				-0.3,
				0.567,
				-0.3,
				1,
				0.778,
				-0.3,
				0.989,
				0.2,
				1.2,
				0.2,
				1,
				1.567,
				0.2,
				1.933,
				-0.2,
				2.3,
				-0.2,
				1,
				2.667,
				-0.2,
				3.033,
				0.1,
				3.4,
				0.1,
				1,
				3.744,
				0.1,
				4.089,
				-0.3,
				4.433,
				-0.3,
				1,
				4.689,
				-0.3,
				4.944,
				0.1,
				5.2,
				0.1,
				1,
				5.544,
				0.1,
				5.889,
				-0.3,
				6.233,
				-0.3,
				1,
				6.6,
				-0.3,
				6.967,
				0.2,
				7.333,
				0.2,
				1,
				7.678,
				0.2,
				8.022,
				-0.4,
				8.367,
				-0.4,
				1,
				8.711,
				-0.4,
				9.056,
				0.2,
				9.4,
				0.2,
				1,
				9.756,
				0.2,
				10.111,
				-0.2,
				10.467,
				-0.2,
				1,
				10.633,
				-0.2,
				10.833,
				-0.087,
				10.967,
				0
			]
		},
		{
			"Target": "Parameter",
			"Id": "Param",
			"Segments": [
				0,
				0,
				1,
				0.125,
				-2.752,
				0.511,
				-9,
				0.7,
				-9,
				1,
				0.911,
				-9,
				1.122,
				6,
				1.333,
				6,
				1,
				1.7,
				6,
				2.067,
				-6,
				2.433,
				-6,
				1,
				2.8,
				-6,
				3.167,
				3,
				3.533,
				3,
				1,
				3.878,
				3,
				4.222,
				-9,
				4.567,
				-9,
				1,
				4.822,
				-9,
				5.078,
				3,
				5.333,
				3,
				1,
				5.678,
				3,
				6.022,
				-10,
				6.367,
				-10,
				1,
				6.733,
				-10,
				7.1,
				4,
				7.467,
				4,
				1,
				7.811,
				4,
				8.156,
				-13,
				8.5,
				-13,
				1,
				8.844,
				-13,
				9.189,
				4,
				9.533,
				4,
				1,
				9.889,
				4,
				10.244,
				-4,
				10.6,
				-4,
				1,
				10.767,
				-4,
				10.6,
				0,
				10.967,
				0
			]
		},
		{
			"Target": "Parameter",
			"Id": "PARAM_HAIR_FRONT1",
			"Segments": [
				0,
				0,
				1,
				0.092,
				-0.168,
				0.311,
				-0.6,
				0.467,
				-0.6,
				1,
				0.678,
				-0.6,
				0.889,
				0.2,
				1.1,
				0.2,
				1,
				1.444,
				0.2,
				1.789,
				-0.5,
				2.133,
				-0.5,
				1,
				2.478,
				-0.5,
				2.822,
				0,
				3.167,
				0,
				1,
				3.544,
				0,
				3.922,
				-0.4,
				4.3,
				-0.4,
				1,
				4.611,
				-0.4,
				4.922,
				0,
				5.233,
				0,
				1,
				5.689,
				0,
				6.144,
				-0.4,
				6.6,
				-0.4,
				1,
				6.889,
				-0.4,
				7.178,
				0,
				7.467,
				0,
				1,
				7.844,
				0,
				8.222,
				-0.4,
				8.6,
				-0.4,
				1,
				8.822,
				-0.4,
				9.044,
				0,
				9.267,
				0,
				1,
				9.656,
				0,
				10.044,
				-0.3,
				10.433,
				-0.3,
				1,
				10.611,
				-0.3,
				10.775,
				-0.15,
				10.967,
				0
			]
		},
		{
			"Target": "Parameter",
			"Id": "PARAM_HAIR_FRONT2",
			"Segments": [
				0,
				0,
				1,
				0.133,
				-0.109,
				0.467,
				-0.4,
				0.7,
				-0.4,
				1,
				0.978,
				-0.4,
				1.256,
				0.2,
				1.533,
				0.2,
				1,
				1.833,
				0.2,
				2.133,
				-0.3,
				2.433,
				-0.3,
				1,
				2.756,
				-0.3,
				3.078,
				0.1,
				3.4,
				0.1,
				1,
				3.811,
				0.1,
				4.222,
				-0.3,
				4.633,
				-0.3,
				1,
				4.978,
				-0.3,
				5.322,
				0.1,
				5.667,
				0.1,
				1,
				6.056,
				0.1,
				6.444,
				-0.3,
				6.833,
				-0.3,
				1,
				7.122,
				-0.3,
				7.411,
				0,
				7.7,
				0,
				1,
				8.011,
				0,
				8.322,
				-0.3,
				8.633,
				-0.3,
				1,
				8.967,
				-0.3,
				9.3,
				0.1,
				9.633,
				0.1,
				1,
				9.933,
				0.1,
				10.233,
				-0.1,
				10.533,
				-0.1,
				1,
				10.678,
				-0.1,
				10.825,
				-0.042,
				10.967,
				0
			]
		},
		{
			"Target": "Parameter",
			"Id": "Param3",
			"Segments": [
				0,
				0,
				1,
				0.158,
				-0.093,
				0.633,
				-0.3,
				0.867,
				-0.3,
				1,
				1.144,
				-0.3,
				1.422,
				0.2,
				1.7,
				0.2,
				1,
				2,
				0.2,
				2.3,
				-0.4,
				2.6,
				-0.4,
				1,
				2.922,
				-0.4,
				3.244,
				0.1,
				3.567,
				0.1,
				1,
				3.978,
				0.1,
				4.389,
				-0.3,
				4.8,
				-0.3,
				1,
				5.144,
				-0.3,
				5.489,
				0.1,
				5.833,
				0.1,
				1,
				6.222,
				0.1,
				6.611,
				-0.3,
				7,
				-0.3,
				1,
				7.289,
				-0.3,
				7.578,
				0,
				7.867,
				0,
				1,
				8.178,
				0,
				8.489,
				-0.3,
				8.8,
				-0.3,
				1,
				9.133,
				-0.3,
				9.467,
				0.1,
				9.8,
				0.1,
				1,
				10.1,
				0.1,
				10.4,
				-0.1,
				10.7,
				-0.1,
				1,
				10.844,
				-0.1,
				10.7,
				0,
				10.967,
				0
			]
		},
		{
			"Target": "Parameter",
			"Id": "PARAM_HEADWEAR1",
			"Segments": [
				0,
				0,
				1,
				0.075,
				-0.118,
				0.267,
				-0.4,
				0.4,
				-0.4,
				1,
				0.6,
				-0.4,
				0.8,
				0.2,
				1,
				0.2,
				1,
				1.267,
				0.2,
				1.533,
				-0.4,
				1.8,
				-0.4,
				1,
				2.078,
				-0.4,
				2.356,
				0,
				2.633,
				0,
				1,
				2.911,
				0,
				3.189,
				-0.3,
				3.467,
				-0.3,
				1,
				3.856,
				-0.3,
				4.244,
				0.3,
				4.633,
				0.3,
				1,
				4.956,
				0.3,
				5.278,
				-0.2,
				5.6,
				-0.2,
				1,
				5.911,
				-0.2,
				6.222,
				0.3,
				6.533,
				0.3,
				1,
				6.833,
				0.3,
				7.133,
				-0.4,
				7.433,
				-0.4,
				1,
				7.856,
				-0.4,
				8.278,
				0.3,
				8.7,
				0.3,
				1,
				9.1,
				0.3,
				9.5,
				-0.3,
				9.9,
				-0.3,
				1,
				10.256,
				-0.3,
				10.633,
				-0.134,
				10.967,
				0
			]
		},
		{
			"Target": "Parameter",
			"Id": "PARAM_HEADWEAR2",
			"Segments": [
				0,
				0,
				1,
				0.083,
				-0.121,
				0.467,
				-0.4,
				0.6,
				-0.4,
				1,
				0.8,
				-0.4,
				1,
				0.2,
				1.2,
				0.2,
				1,
				1.467,
				0.2,
				1.733,
				-0.3,
				2,
				-0.3,
				1,
				2.278,
				-0.3,
				2.556,
				0,
				2.833,
				0,
				1,
				3.111,
				0,
				3.389,
				-0.3,
				3.667,
				-0.3,
				1,
				4.056,
				-0.3,
				4.444,
				0.3,
				4.833,
				0.3,
				1,
				5.156,
				0.3,
				5.478,
				-0.2,
				5.8,
				-0.2,
				1,
				6.111,
				-0.2,
				6.422,
				0.3,
				6.733,
				0.3,
				1,
				7.033,
				0.3,
				7.333,
				-0.4,
				7.633,
				-0.4,
				1,
				8.056,
				-0.4,
				8.478,
				0.3,
				8.9,
				0.3,
				1,
				9.3,
				0.3,
				9.7,
				-0.3,
				10.1,
				-0.3,
				1,
				10.456,
				-0.3,
				10.278,
				0,
				10.967,
				0
			]
		},
		{
			"Target": "Parameter",
			"Id": "PARAM_QUNZI",
			"Segments": [
				0,
				0,
				1,
				3.656,
				0,
				7.311,
				0,
				10.967,
				0
			]
		},
		{
			"Target": "Parameter",
			"Id": "PARAM_Tears",
			"Segments": [
				0,
				0,
				1,
				3.656,
				0,
				7.311,
				0,
				10.967,
				0
			]
		},
		{
			"Target": "Parameter",
			"Id": "PARAM_flash",
			"Segments": [
				0,
				0,
				1,
				3.656,
				0,
				7.311,
				0,
				10.967,
				0
			]
		},
		{
			"Target": "Parameter",
			"Id": "PARAM_awkward",
			"Segments": [
				0,
				0,
				1,
				3.656,
				0,
				7.311,
				0,
				10.967,
				0
			]
		},
		{
			"Target": "Parameter",
			"Id": "PARAM_gas",
			"Segments": [
				0,
				0,
				1,
				3.656,
				0,
				7.311,
				0,
				10.967,
				0
			]
		},
		{
			"Target": "Parameter",
			"Id": "PARAM_LOVE1",
			"Segments": [
				0,
				0,
				1,
				3.656,
				0,
				7.311,
				0,
				10.967,
				0
			]
		},
		{
			"Target": "Parameter",
			"Id": "PARAM_LOVE2",
			"Segments": [
				0,
				0,
				1,
				3.656,
				0,
				7.311,
				0,
				10.967,
				0
			]
		},
		{
			"Target": "Parameter",
			"Id": "PARAM_angry1",
			"Segments": [
				0,
				0,
				1,
				3.656,
				0,
				7.311,
				0,
				10.967,
				0
			]
		},
		{
			"Target": "Parameter",
			"Id": "PARAM_angry2",
			"Segments": [
				0,
				0,
				1,
				3.656,
				0,
				7.311,
				0,
				10.967,
				0
			]
		},
		{
			"Target": "Parameter",
			"Id": "PARAM_face",
			"Segments": [
				0,
				0,
				1,
				3.656,
				0,
				7.311,
				0,
				10.967,
				0
			]
		},
		{
			"Target": "Parameter",
			"Id": "PARAM_SUN",
			"Segments": [
				0,
				0,
				1,
				3.656,
				0,
				7.311,
				0,
				10.967,
				0
			]
		},
		{
			"Target": "Parameter",
			"Id": "PARAM_Ding_Dong",
			"Segments": [
				0,
				0,
				1,
				3.656,
				0,
				7.311,
				0,
				10.967,
				0
			]
		},
		{
			"Target": "Parameter",
			"Id": "PARAM_sweat",
			"Segments": [
				0,
				0,
				1,
				3.656,
				0,
				7.311,
				0,
				10.967,
				0
			]
		},
		{
			"Target": "Parameter",
			"Id": "PARAM_light",
			"Segments": [
				0,
				0,
				1,
				3.656,
				0,
				7.311,
				0,
				10.967,
				0
			]
		},
		{
			"Target": "Parameter",
			"Id": "PARAM_shock",
			"Segments": [
				0,
				0,
				1,
				3.656,
				0,
				7.311,
				0,
				10.967,
				0
			]
		}
	]
}